setup.cfg
setup.py
iFlux.egg-info/PKG-INFO
iFlux.egg-info/SOURCES.txt
iFlux.egg-info/dependency_links.txt
iFlux.egg-info/entry_points.txt
iFlux.egg-info/requires.txt
iFlux.egg-info/top_level.txt
iflux/__init__.py
iflux/conf.py
iflux/bin/iflux-admin.py
iflux/conf/iflux.ini
iflux/core/__init__.py
iflux/core/handlers.py
iflux/core/security.py
iflux/core/template.py
iflux/core/data/__init__.py
iflux/core/data/handlers.py
iflux/core/data/orm.py
iflux/core/scaffolding/__init__.py
iflux/core/session/__init__.py
iflux/core/session/handlers.py
iflux/modules/__init__.py
iflux/modules/admin/__init__.py
iflux/modules/admin/handlers.py
iflux/modules/admin/models.py
iflux/modules/admin/templates/admin_base.html
iflux/modules/admin/templates/dashboard.html
iflux/modules/iflux/__init__.py
iflux/modules/iflux/handlers.py
iflux/modules/iflux/templates/info.html
iflux/util/__init__.py
iflux/util/file.py
iflux/util/mixin.py
iflux/util/sqlalchemy_util.py
iflux/util/url.py